setup.py
dict_compare/__init__.py
dict_compare/dict_compare.py
dict_compare/json_filter.py
test/test_dict_compare.py
yadict_compare.egg-info/PKG-INFO
yadict_compare.egg-info/SOURCES.txt
yadict_compare.egg-info/dependency_links.txt
yadict_compare.egg-info/top_level.txt