Metadata-Version: 1.1
Name: yadict-compare
Version: 1.2.0
Summary: Yet another dictionary comparison tool with filtering and reporting
Home-page: http://github.com/hsolbrig/dict_compare
Author: Harold Solbrig
Author-email: solbrig.harold@mayo.edu
License: BSD 3-Clause license
Platform: UNKNOWN
Classifier: Topic :: Software Development :: Libraries
Classifier: Programming Language :: Python :: 3
Classifier: Programming Language :: Python :: 3 :: Only
